xenfra_sdk/__init__.py
xenfra_sdk/cli/__init__.py
xenfra_sdk/cli/main.py
xenfra_sdk/client.py
xenfra_sdk/client_with_hooks.py
xenfra_sdk/config.py
xenfra_sdk/db/__init__.py
xenfra_sdk/db/models.py
xenfra_sdk/db/session.py
xenfra_sdk/dependencies.py
xenfra_sdk/detection.py
xenfra_sdk/dockerizer.py
xenfra_sdk/engine.py
xenfra_sdk/exceptions.py
xenfra_sdk/manifest.py
xenfra_sdk/mcp_client.py
xenfra_sdk/models.py
xenfra_sdk/orchestrator.py
xenfra_sdk/patterns.json
xenfra_sdk/privacy.py
xenfra_sdk/recipes.py
xenfra_sdk/resources/__init__.py
xenfra_sdk/resources/base.py
xenfra_sdk/resources/deployments.py
xenfra_sdk/resources/files.py
xenfra_sdk/resources/intelligence.py
xenfra_sdk/resources/projects.py
xenfra_sdk/security.py
xenfra_sdk/security_scanner.py
xenfra_sdk/templates/Caddyfile.j2
xenfra_sdk/templates/Dockerfile.j2
xenfra_sdk/templates/cloud-init.sh.j2
xenfra_sdk/templates/docker-compose-multi.yml.j2
xenfra_sdk/templates/docker-compose.yml.j2
xenfra_sdk/utils.py
xenfra_sdk-0.2.5.dist-info/WHEEL
xenfra_sdk-0.2.5.dist-info/METADATA
xenfra_sdk-0.2.5.dist-info/RECORD
