Metadata-Version: 2.3
Name: xenfra-sdk
Version: 0.2.5
Summary: Xenfra SDK: Core engine and utilities for the Xenfra platform.
Author: xenfra-cloud
Author-email: xenfra-cloud <xenfracloud@gmail.com>
Classifier: Programming Language :: Python :: 3
Classifier: License :: OSI Approved :: MIT License
Classifier: Operating System :: OS Independent
Classifier: Development Status :: 3 - Alpha
Classifier: Intended Audience :: Developers
Classifier: Topic :: Software Development :: Build Tools
Classifier: Topic :: System :: Systems Administration
Requires-Dist: fabric>=3.2.2
Requires-Dist: python-digitalocean>=1.17.0
Requires-Dist: python-dotenv>=1.2.1
Requires-Dist: rich>=14.2.0
Requires-Dist: sqlmodel>=0.0.16
Requires-Dist: pyyaml>=6.0.1
Requires-Dist: httpx>=0.27.0
Requires-Dist: jinja2>=3.1.3
Requires-Dist: python-jose[cryptography]>=3.3.0
Requires-Dist: passlib>=1.7.4
Requires-Dist: cryptography>=41.0.0
Requires-Dist: pytest>=8.0.0 ; extra == 'dev'
Requires-Dist: pytest-mock>=3.12.0 ; extra == 'dev'
Requires-Dist: pytest-cov>=4.0.0 ; extra == 'dev'
Requires-Dist: pytest-asyncio>=0.21.0 ; extra == 'dev'
Requires-Python: >=3.11
Project-URL: Homepage, https://github.com/xenfra-cloud/xenfra-sdk
Project-URL: Issues, https://github.com/xenfra-cloud/xenfra-sdk/issues
Provides-Extra: dev
